shipzo_plus/__init__.py
shipzo_plus/shipzo_plus.py
shipzo_plus-0.1.4.dist-info/METADATA
shipzo_plus-0.1.4.dist-info/WHEEL
shipzo_plus-0.1.4.dist-info/entry_points.txt
shipzo_plus-0.1.4.dist-info/top_level.txt
shipzo_plus-0.1.4.dist-info/RECORD
